ADRpy/__init__.py
ADRpy/airworthiness.py
ADRpy/atmospheres.py
ADRpy/constraintanalysis.py
ADRpy/mtools4acdc.py
ADRpy/propulsion.py
ADRpy/unitconversions.py
ADRpy/weathertools.py
ADRpy/data/.DS_Store
ADRpy/data/elev1200m.dat
ADRpy/data/runways.csv
ADRpy/data/sample_takeoff_data.csv
ADRpy/data/_MHDBK310/high_dens_at_10km.m310
ADRpy/data/_MHDBK310/high_dens_at_20km.m310
ADRpy/data/_MHDBK310/high_dens_at_5km.m310
ADRpy/data/_MHDBK310/high_temp_at_10km.m310
ADRpy/data/_MHDBK310/high_temp_at_20km.m310
ADRpy/data/_MHDBK310/high_temp_at_5km.m310
ADRpy/data/_MHDBK310/low_dens_at_10km.m310
ADRpy/data/_MHDBK310/low_dens_at_20km.m310
ADRpy/data/_MHDBK310/low_dens_at_5km.m310
ADRpy/data/_MHDBK310/low_temp_at_10km.m310
ADRpy/data/_MHDBK310/low_temp_at_20km.m310
ADRpy/data/_MHDBK310/low_temp_at_5km.m310
ADRpy/data/engine_data/Electric_CSVs/JMX57_Efficiency_data.csv
ADRpy/data/engine_data/Electric_CSVs/YASA_750R_Efficiency_data.csv
ADRpy/data/engine_data/Electric_CSVs/_electric_metadata.csv
ADRpy/data/engine_data/Jet_CSVs/ATF3-6A_Sea_level_thrust_polynomial.csv
ADRpy/data/engine_data/Jet_CSVs/ATF3-6A_TSFC_data.csv
ADRpy/data/engine_data/Jet_CSVs/ATF3-6A_Thrust_data.csv
ADRpy/data/engine_data/Jet_CSVs/F404-400_Sea_level_thrust_polynomial.csv
ADRpy/data/engine_data/Jet_CSVs/F404-400_Thrust_data.csv
ADRpy/data/engine_data/Jet_CSVs/FJ-44_Sea_level_thrust_polynomial.csv
ADRpy/data/engine_data/Jet_CSVs/FJ-44_TSFC_data.csv
ADRpy/data/engine_data/Jet_CSVs/FJ-44_Thrust_data.csv
ADRpy/data/engine_data/Jet_CSVs/J52_Sea_level_thrust_polynomial.csv
ADRpy/data/engine_data/Jet_CSVs/J52_TSFC_data.csv
ADRpy/data/engine_data/Jet_CSVs/J52_Thrust_data.csv
ADRpy/data/engine_data/Jet_CSVs/J60_Sea_level_thrust_polynomial.csv
ADRpy/data/engine_data/Jet_CSVs/J60_TSFC_data.csv
ADRpy/data/engine_data/Jet_CSVs/J60_Thrust_data.csv
ADRpy/data/engine_data/Jet_CSVs/JT8D-9_Sea_level_take_off_thrust_polynomial.csv
ADRpy/data/engine_data/Jet_CSVs/JT8D-9_Sea_level_thrust_polynomial.csv
ADRpy-0.2.6.dist-info/LICENSE.md
ADRpy-0.2.6.dist-info/METADATA
ADRpy-0.2.6.dist-info/WHEEL
ADRpy-0.2.6.dist-info/top_level.txt
ADRpy-0.2.6.dist-info/RECORD
