Metadata-Version: 2.1
Name: ADRpy
Version: 0.2.6
Summary: Aircraft Design Recipes in Python: a library of aircraft conceptual design tools.
Home-page: https://github.com/sobester/ADRpy
Download-URL: https://github.com/sobester/ADRpy/tarball/0.2.6
Author: Andras Sobester
Author-email: 
License: GPLv3
Classifier: Development Status :: 3 - Alpha
Classifier: Intended Audience :: Developers
Classifier: Programming Language :: Python :: 3
Classifier: Topic :: Scientific/Engineering
License-File: LICENSE.md
Requires-Dist: sphinx
Requires-Dist: sphinx-rtd-theme
Requires-Dist: nose
Requires-Dist: coverage
Requires-Dist: scipy
Requires-Dist: pandas
Requires-Dist: cycler
Requires-Dist: matplotlib
Requires-Dist: pytest >=4.3.0
